SpaSRL/__init__.py
SpaSRL/_compat.py
SpaSRL/_expression_denoising.py
SpaSRL/_initialize.py
SpaSRL/_lasso_landmarks.py
SpaSRL/_meta_genes.py
SpaSRL/_select_landmarks.py
SpaSRL/_solve.py
SpaSRL/_spatial_enhancement.py
SpaSRL/_srl.py
SpaSRL/_utils.py
spasrl-0.1.2.dist-info/WHEEL
spasrl-0.1.2.dist-info/METADATA
spasrl-0.1.2.dist-info/RECORD
